liontools/__init__.py
liontools/git-branches-rename
liontools/git-clone-subset
liontools/git-find-uncommitted-repos
liontools/git-rebase-theirs
liontools/git-restore-mtime
liontools/git-strip-merge
liontools/runner.py
liontools-0.0.1.dist-info/METADATA
liontools-0.0.1.dist-info/WHEEL
liontools-0.0.1.dist-info/entry_points.txt
liontools-0.0.1.dist-info/top_level.txt
liontools-0.0.1.dist-info/RECORD
