Metadata-Version: 2.1
Name: liontools
Version: 0.0.1
Summary: Assorted git-related scripts and tools
Author-email: "Rodrigo Silva (MestreLion)" <linux@rodrigosilva.com>, Alex Kalaverin <alex@kalaver.in>
License: GNU General Public License v3 or later (GPLv3+)
Project-URL: Homepage, https://github.com/MestreLion/git-tools
Project-URL: Issues, https://github.com/MestreLion/git-tools/issues
Project-URL: Repository, https://github.com/MestreLion/git-tools
Keywords: git,tools,scripts,automation,version control,repository,python,git-restore-mtime,git-clone-subset,git-rebase-theirs,git-find-uncommitted-repos,git-branches-rename,git-strip-merge
Classifier: Development Status :: 5 - Production/Stable
Classifier: Intended Audience :: Developers
Classifier: License :: OSI Approved :: GNU General Public License v3 or later (GPLv3+)
Classifier: Programming Language :: Python :: 3
Classifier: Programming Language :: Python :: 3.8
Classifier: Programming Language :: Python :: 3.9
Classifier: Programming Language :: Python :: 3.10
Classifier: Programming Language :: Python :: 3.11
Classifier: Topic :: Software Development :: Version Control :: Git
Classifier: Operating System :: POSIX :: Linux
Classifier: Operating System :: MacOS
Classifier: Operating System :: Microsoft :: Windows
Requires-Python: >=3.8
